[1,["335uGgd4FLWLbnVEK3VG7Z@6c48a"],0,[["sp.SkeletonData",["_name","_atlasText","textureNames","_skeletonJson","textures"],-1,3]],[[0,0,1,2,3,4,5]],[[0,"bj","\nbj.png\nsize: 890,660\nformat: RGBA8888\nfilter: Linear,Linear\nrepeat: none\n0\n  rotate: false\n  xy: 720, 395\n  size: 168, 263\n  orig: 170, 270\n  offset: 1, 6\n  index: -1\n022\n  rotate: true\n  xy: 2, 2\n  size: 656, 716\n  orig: 728, 747\n  offset: 36, 30\n  index: -1\nyuan\n  rotate: false\n  xy: 720, 309\n  size: 87, 84\n  orig: 93, 90\n  offset: 3, 3\n  index: -1\n",["bj.png"],{"skeleton":{"hash":"vA7D8yURAgmpcWDRfn1NbgTPArs","spine":"3.8.75","x":-602.48,"y":0.97,"width":1198.62,"height":1368.08,"images":"D:/project/18.箭了又箭/动画/背景动画/images/","audio":"D:\\project\\18.箭了又箭\\动画\\背景动画"},"bones":[{"name":"root"},{"name":"bone","parent":"root","length":251.2,"rotation":90.33,"x":-4.99,"y":368.5},{"name":"bone2","parent":"root","length":164.67,"rotation":88.99,"x":214.61,"y":846.49},{"name":"bone3","parent":"root","length":226.29,"rotation":91.85,"x":-266.13,"y":1158.82},{"name":"bone4","parent":"root","length":128.35,"rotation":88.53,"x":-241.84,"y":425.83},{"name":"bone5","parent":"root","length":94.02,"rotation":87.51,"x":100.89,"y":1010.95},{"name":"bone6","parent":"root","length":87.83,"rotation":88.67,"x":113.14,"y":1264.16},{"name":"bone7","parent":"root","length":91.89,"rotation":90,"x":270.38,"y":1278.45},{"name":"bone8","parent":"root","length":134.77,"rotation":90,"x":-141.44,"y":933.99},{"name":"bone9","parent":"root","x":-142.37,"y":1154.38},{"name":"bone10","parent":"bone9","length":13.21,"rotation":90,"x":-59.33,"y":-27.87},{"name":"bone11","parent":"bone9","length":15.78,"rotation":113.5,"x":-53.04,"y":45.72},{"name":"bone12","parent":"bone9","length":19.66,"rotation":82.65,"x":67.1,"y":115.54},{"name":"bone13","parent":"bone9","length":13.84,"rotation":90,"x":-161.23,"y":-53.03},{"name":"bone14","parent":"bone9","length":16.4,"rotation":85.6,"x":-135.44,"y":87.24}],"slots":[{"name":"0","bone":"bone2","attachment":"0"},{"name":"yuan","bone":"bone3"},{"name":"022","bone":"bone","attachment":"022"},{"name":"1","bone":"bone5","attachment":"0"},{"name":"2","bone":"bone4","attachment":"0"},{"name":"3","bone":"bone8","attachment":"0"},{"name":"4","bone":"bone6","attachment":"0"},{"name":"5","bone":"bone7","attachment":"0"},{"name":"22","bone":"bone3"},{"name":"yuan2","bone":"bone12","attachment":"yuan"},{"name":"yuan3","bone":"bone13","attachment":"yuan"},{"name":"yuan4","bone":"bone11","attachment":"yuan"},{"name":"yuan5","bone":"bone14","attachment":"yuan"},{"name":"yuan6","bone":"bone10","attachment":"yuan"}],"skins":[{"name":"default","attachments":{"0":{"0":{"x":60.49,"y":-3.13,"rotation":-88.99,"width":170,"height":270}},"1":{"0":{"x":40.62,"y":-0.65,"scaleX":0.4367,"scaleY":0.4367,"rotation":-87.51,"width":170,"height":270}},"2":{"0":{"x":72.13,"y":-4.18,"scaleX":0.5812,"scaleY":0.5812,"rotation":-88.53,"width":170,"height":270}},"3":{"0":{"x":62.45,"y":0.78,"scaleX":0.6947,"scaleY":0.6947,"rotation":-90,"width":170,"height":270}},"4":{"0":{"x":37.4,"y":-2.68,"scaleX":0.4222,"scaleY":0.4222,"rotation":-88.67,"width":170,"height":270}},"5":{"0":{"x":31.96,"y":0.42,"scaleX":0.4344,"scaleY":0.4344,"rotation":-90,"width":170,"height":270}},"022":{"022":{"x":69.96,"y":-2.21,"scaleX":1.6465,"rotation":-90.33,"width":728,"height":747}},"yuan":{"yuan":{"x":16.99,"y":-36.37,"scaleX":9.8885,"scaleY":9.8885,"rotation":-91.85,"width":93,"height":90}},"yuan3":{"yuan":{"x":3.53,"y":-0.26,"scaleX":0.1971,"scaleY":0.1971,"rotation":-90,"width":93,"height":90}},"yuan4":{"yuan":{"x":1.84,"y":0.56,"scaleX":0.2467,"scaleY":0.2467,"rotation":-113.5,"width":93,"height":90}},"yuan5":{"yuan":{"x":5.29,"y":-4.08,"scaleX":0.3433,"scaleY":0.3433,"rotation":-85.6,"width":93,"height":90}},"yuan6":{"yuan":{"x":3.38,"y":-1.71,"scaleX":0.0978,"scaleY":0.0978,"rotation":-90,"width":93,"height":90}},"yuan2":{"yuan":{"x":3.34,"y":0.12,"scaleX":0.233,"scaleY":0.233,"rotation":-82.65,"width":93,"height":90}}}}],"animations":{"animation":{"slots":{"0":{"color":[{"color":"ffffff00"},{"time":1,"color":"ffffffff"},{"time":2,"color":"ffffff00"}]},"1":{"color":[{"color":"ffffff00","curve":"stepped"},{"time":0.1667,"color":"ffffff00"},{"time":0.8333,"color":"ffffff93"},{"time":1,"color":"ffffff00"}]},"2":{"color":[{"color":"ffffff00","curve":"stepped"},{"time":0.5,"color":"ffffff00"},{"time":1.2,"color":"ffffffad"},{"time":1.6667,"color":"ffffff00"}]},"3":{"color":[{"color":"ffffff00","curve":"stepped"},{"time":0.5,"color":"ffffff00"},{"time":1.5,"color":"ffffff79"}]},"4":{"color":[{"color":"ffffff00"},{"time":0.5,"color":"ffffffa2"},{"time":0.8333,"color":"ffffff00"}]},"5":{"color":[{"color":"ffffff00","curve":"stepped"},{"time":0.6667,"color":"ffffff00"},{"time":1.7333,"color":"ffffff93"},{"time":1.7667,"color":"ffffff00"}]},"yuan3":{"color":[{"color":"ffffff00","curve":"stepped"},{"time":0.1667,"color":"ffffff00"},{"time":0.5,"color":"ffffffb9"},{"time":0.8333,"color":"ffffff00"}]},"yuan5":{"color":[{"color":"ffffff00","curve":"stepped"},{"time":0.8333,"color":"ffffff00"},{"time":1.4333,"color":"ffffffb6"},{"time":1.6667,"color":"ffffff00"}]},"yuan4":{"color":[{"color":"ffffff00","curve":"stepped"},{"time":0.5,"color":"ffffff00"},{"time":1.2,"color":"ffffffb6"},{"time":1.5,"color":"ffffff00"}]},"022":{"color":[{"color":"ffffff00"},{"time":0.3333,"color":"ffffff59"},{"time":0.6667,"color":"ffffffff"},{"time":1,"color":"ffffff59"},{"time":1.3333,"color":"ffffffff"},{"time":1.6667,"color":"ffffff4c"},{"time":2,"color":"ffffff00"}]},"yuan2":{"color":[{"color":"ffffff00","curve":"stepped"},{"time":0.2333,"color":"ffffff00"},{"time":0.6667,"color":"ffffff9e"},{"time":1.3667,"color":"ffffff00"}]},"yuan6":{"color":[{"color":"ffffff00"},{"time":1,"color":"ffffffff"},{"time":2,"color":"ffffff00"}]},"yuan":{"color":[{"color":"ffffff6e"},{"time":0.5,"color":"ffffff59"},{"time":1,"color":"ffffffcc"},{"time":1.5,"color":"ffffff42"},{"time":2,"color":"ffffff6e"}]}},"bones":{"bone":{"translate":[{"x":2.3,"y":-397.98},{"time":2,"x":-5.54,"y":959.18}]},"bone2":{"translate":[{"x":66.9,"y":-578.81},{"time":2,"x":87.58,"y":589.33}]},"bone3":{"scale":[{"x":0.814,"y":0.814},{"time":1,"x":1.296,"y":1.296},{"time":2,"x":0.872,"y":0.872}]},"bone8":{"translate":[{"time":0.5,"y":-842.44},{"time":1.5,"y":458.68}]},"bone5":{"translate":[{"time":0.1667},{"time":0.8333,"x":17.43,"y":400.83}]},"bone7":{"translate":[{"time":0.6667,"y":-1016.95},{"time":1.7333,"y":-214.92}]},"bone6":{"translate":[{"x":-31.18,"y":-1340.56},{"time":0.8333,"x":-15.36,"y":-660.54}]},"bone4":{"translate":[{"time":0.5,"x":-9.26,"y":-361.19},{"time":1.6667,"x":10.41,"y":406.1}]},"bone13":{"translate":[{"time":0.1667,"y":-95.86},{"time":0.8333,"y":92.96}]},"bone11":{"translate":[{"time":0.5,"x":13.14,"y":-30.23},{"time":1.5,"x":-51.44,"y":118.32}]},"bone10":{"translate":[{"y":-97.34},{"time":2,"y":236.29}]},"bone14":{"translate":[{"time":0.8333},{"time":1.6667,"x":9.01,"y":117.18}]},"bone12":{"translate":[{"time":0.2333,"x":-31.44,"y":-243.69},{"time":1.3667,"x":-4.78,"y":-37.04}]}}}}},[0]]],0,0,[0],[-1],[0]]
